{
  "version": 4,
  "tempo": 120,
  "timeSigType": 0,
  "masterVolume": 0.5,
  "masterPan": 0.5,
  "masterAutos": [
    { "state": true, "sections": [] },
    {
      "state": true,
      "sections": [
        {
          "startTick": 0,
          "length": 261120,
          "nodes": [
            { "position": 0, "value": 0.22484278678894043 },
            { "position": 1920, "value": 0.22484278678894043 }
          ]
        }
      ]
    },
    { "state": true, "sections": [] }
  ],
  "tracks": [
    {
      "type": 3,
      "label": "Overdriven Guitar",
      "volume": 0.5,
      "pan": 0.5,
      "muteState": 0,
      "solo": false,
      "showingAuto": true,
      "currentAutoIndex": 4,
      "scTrackIndex": -1,
      "filePath": "/storage/emulated/0/玩酷电音/SoundFont/The_DEFINITIVE_MEGALOVANIA_Soundfont__V1.17.sf2",
      "presetIndex": 0,
      "pitchRange": 1,
      "sections": [
        {
          "startTick": 0,
          "length": 15360,
          "startOffsetTick": 0,
          "endOffsetTick": 0,
          "notes": [
            { "startTick": 0, "length": 120, "key": 46, "volume": 1 },
            { "startTick": 120, "length": 120, "key": 46, "volume": 1 },
            { "startTick": 240, "length": 120, "key": 49, "volume": 1 },
            { "startTick": 360, "length": 120, "key": 51, "volume": 1 },
            { "startTick": 480, "length": 240, "key": 56, "volume": 1 },
            { "startTick": 720, "length": 240, "key": 49, "volume": 1 },
            { "startTick": 960, "length": 120, "key": 46, "volume": 1 },
            { "startTick": 1080, "length": 240, "key": 49, "volume": 1 },
            { "startTick": 1320, "length": 240, "key": 53, "volume": 1 },
            { "startTick": 1560, "length": 120, "key": 52, "volume": 1 },
            { "startTick": 1680, "length": 120, "key": 51, "volume": 1 },
            { "startTick": 1800, "length": 120, "key": 49, "volume": 1 },
            { "startTick": 1920, "length": 120, "key": 44, "volume": 1 },
            { "startTick": 2040, "length": 120, "key": 44, "volume": 1 },
            { "startTick": 2160, "length": 120, "key": 49, "volume": 1 },
            { "startTick": 2280, "length": 120, "key": 51, "volume": 1 },
            { "startTick": 2400, "length": 240, "key": 56, "volume": 1 },
            { "startTick": 2640, "length": 240, "key": 49, "volume": 1 },
            { "startTick": 2880, "length": 120, "key": 44, "volume": 1 },
            { "startTick": 3000, "length": 120, "key": 49, "volume": 1 },
            { "startTick": 3120, "length": 120, "key": 44, "volume": 1 },
            { "startTick": 3240, "length": 360, "key": 53, "volume": 1 },
            { "startTick": 3600, "length": 240, "key": 52, "volume": 1 },
            { "startTick": 3840, "length": 120, "key": 42, "volume": 1 },
            { "startTick": 3960, "length": 120, "key": 42, "volume": 1 },
            { "startTick": 4080, "length": 120, "key": 49, "volume": 1 },
            { "startTick": 4080, "length": 120, "key": 49, "volume": 1 },
            { "startTick": 4200, "length": 120, "key": 51, "volume": 1 },
            { "startTick": 4200, "length": 120, "key": 51, "volume": 1 },
            { "startTick": 4320, "length": 240, "key": 56, "volume": 1 },
            { "startTick": 4320, "length": 240, "key": 56, "volume": 1 },
            { "startTick": 4560, "length": 240, "key": 49, "volume": 1 },
            { "startTick": 4800, "length": 120, "key": 42, "volume": 1 },
            { "startTick": 4920, "length": 240, "key": 49, "volume": 1 },
            { "startTick": 5160, "length": 240, "key": 53, "volume": 1 },
            { "startTick": 5400, "length": 120, "key": 52, "volume": 1 },
            { "startTick": 5520, "length": 120, "key": 51, "volume": 1 },
            { "startTick": 5640, "length": 120, "key": 49, "volume": 1 },
            { "startTick": 5760, "length": 240, "key": 41, "volume": 1 },
            { "startTick": 6000, "length": 240, "key": 56, "volume": 1 },
            { "startTick": 6240, "length": 120, "key": 53, "volume": 1 },
            { "startTick": 6360, "length": 120, "key": 51, "volume": 1 },
            { "startTick": 6480, "length": 120, "key": 49, "volume": 1 },
            { "startTick": 6600, "length": 120, "key": 44, "volume": 1 },
            { "startTick": 6720, "length": 240, "key": 49, "volume": 1 },
            { "startTick": 6960, "length": 240, "key": 48, "volume": 1 },
            { "startTick": 7200, "length": 480, "key": 45, "volume": 1 }
          ]
        }
      ],
      "autos": [
        {
          "state": false,
          "sections": [{ "startTick": 15360, "length": 1920, "nodes": [] }]
        },
        { "state": false, "sections": [] },
        { "state": false, "sections": [] },
        { "state": false, "sections": [] },
        { "state": true, "sections": [] },
        { "state": false, "sections": [] },
        { "state": true, "sections": [] },
        { "state": false, "sections": [] },
        { "state": false, "sections": [] },
        { "state": false, "sections": [] },
        { "state": false, "sections": [] }
      ],
      "fx": [
        0,
        0,
        0,
        0.4075033664703369,
        0.40148067474365234,
        0.6000000238418579,
        0.20000000298023224,
        0.49152544140815735,
        0,
        1,
        0.5714285969734192,
        0,
        0.75,
        [0, 0, 0, 0],
        [0.5, 0.5, 0.5, 0.5],
        [
          0.0030030030757188797, 0.011511511169373989, 0.19919919967651367,
          0.5995995998382568
        ],
        [
          0.08994708955287933, 0.05128205567598343, 0.05128205567598343,
          0.08994708955287933
        ],
        1,
        0.07999998331069946,
        0.8000000715255737,
        0,
        0.4000000059604645,
        0,
        0,
        0.75,
        0.4444444477558136,
        0.625,
        0.4000000059604645,
        0.30769234895706177,
        0.40000003576278687,
        0.5,
        0.8333333134651184,
        0.111111119389534,
        0.4285714626312256,
        0.1666666716337204
      ],
      "fxState": [true, false, false, false, false, false, false, false]
    },
    {
      "type": 3,
      "label": "Undertale Violin",
      "volume": 0.5,
      "pan": 0.5,
      "muteState": 0,
      "solo": false,
      "showingAuto": true,
      "currentAutoIndex": 0,
      "scTrackIndex": -1,
      "filePath": "/storage/emulated/0/玩酷电音/SoundFont/undertale.sf2",
      "presetIndex": 3,
      "pitchRange": 1,
      "sections": [],
      "autos": [
        { "state": true, "sections": [] },
        { "state": false, "sections": [] },
        { "state": false, "sections": [] },
        { "state": false, "sections": [] },
        { "state": false, "sections": [] },
        { "state": false, "sections": [] },
        { "state": false, "sections": [] },
        { "state": false, "sections": [] },
        { "state": false, "sections": [] },
        { "state": false, "sections": [] },
        { "state": false, "sections": [] }
      ],
      "fx": [
        0,
        0,
        0,
        1,
        1,
        0.6000000238418579,
        0.20000000298023224,
        0.49152544140815735,
        0,
        1,
        0.5714285969734192,
        0,
        0.75,
        [0, 0, 0, 0],
        [0.5, 0.5, 0.5, 0.5],
        [
          0.0030030030757188797, 0.011511511169373989, 0.19919919967651367,
          0.5995995998382568
        ],
        [
          0.08994708955287933, 0.05128205567598343, 0.05128205567598343,
          0.08994708955287933
        ],
        1,
        0.07999998331069946,
        0.8000000715255737,
        0,
        0.4000000059604645,
        0,
        0,
        0.75,
        0.4444444477558136,
        0.625,
        0.4000000059604645,
        0.30769234895706177,
        0.40000003576278687,
        0.5,
        0.8333333134651184,
        0.111111119389534,
        0.4285714626312256,
        0.1666666716337204
      ],
      "fxState": [true, false, true, false, false, false, false, false]
    },
    {
      "type": 3,
      "label": "Undying Bells",
      "volume": 0.5,
      "pan": 0.5,
      "muteState": 0,
      "solo": false,
      "showingAuto": true,
      "currentAutoIndex": 4,
      "scTrackIndex": -1,
      "filePath": "/storage/emulated/0/玩酷电音/SoundFont/undertale.sf2",
      "presetIndex": 87,
      "pitchRange": 1,
      "sections": [],
      "autos": [
        { "state": false, "sections": [] },
        { "state": false, "sections": [] },
        { "state": false, "sections": [] },
        { "state": false, "sections": [] },
        { "state": false, "sections": [] },
        { "state": false, "sections": [] },
        { "state": false, "sections": [] },
        { "state": false, "sections": [] },
        { "state": false, "sections": [] },
        { "state": false, "sections": [] },
        { "state": false, "sections": [] }
      ],
      "fx": [
        0.36666664481163025,
        0.9473683834075928,
        0.6097561120986938,
        0.8999999761581421,
        1,
        0.6000000238418579,
        0.20000000298023224,
        0.49152544140815735,
        0,
        1,
        0.5714285969734192,
        0,
        0.75,
        [0, 0, 0, 0],
        [0.5, 0.5, 0.5, 0.5],
        [
          0.0030030030757188797, 0.011511511169373989, 0.19919919967651367,
          0.5995995998382568
        ],
        [
          0.08994708955287933, 0.05128205567598343, 0.05128205567598343,
          0.08994708955287933
        ],
        1,
        0.07999998331069946,
        0.8000000715255737,
        0,
        0.4000000059604645,
        0,
        0,
        0.75,
        0.4444444477558136,
        0.625,
        0.4000000059604645,
        0.30769234895706177,
        0.40000003576278687,
        0.5,
        0.8333333134651184,
        0.111111119389534,
        0.4285714626312256,
        0.1666666716337204
      ],
      "fxState": [false, false, false, false, false, false, false, false]
    },
    {
      "type": 3,
      "label": "hypersawwave",
      "volume": 0.5,
      "pan": 0.5,
      "muteState": 0,
      "solo": false,
      "showingAuto": false,
      "currentAutoIndex": 0,
      "scTrackIndex": -1,
      "filePath": "/storage/emulated/0/玩酷电音/SoundFont/Hyper Saw.sf2",
      "presetIndex": 0,
      "pitchRange": 1,
      "sections": [],
      "autos": [
        { "state": false, "sections": [] },
        { "state": false, "sections": [] },
        { "state": false, "sections": [] },
        { "state": false, "sections": [] },
        { "state": false, "sections": [] },
        { "state": false, "sections": [] },
        { "state": false, "sections": [] },
        { "state": false, "sections": [] },
        { "state": false, "sections": [] },
        { "state": false, "sections": [] },
        { "state": false, "sections": [] }
      ],
      "fx": [
        0,
        0,
        0,
        0.4010002613067627,
        0.4060000479221344,
        0.6000000238418579,
        0.20000000298023224,
        0.49152544140815735,
        0,
        1,
        0.5714285969734192,
        0,
        0.75,
        [0, 0, 0, 0],
        [0.5, 0.5, 0.5, 0.5],
        [
          0.0030030030757188797, 0.011511511169373989, 0.19919919967651367,
          0.5995995998382568
        ],
        [
          0.08994708955287933, 0.05128205567598343, 0.05128205567598343,
          0.08994708955287933
        ],
        1,
        0.07999998331069946,
        0.8000000715255737,
        0,
        0.4000000059604645,
        0,
        0,
        0.75,
        0.4444444477558136,
        0.625,
        0.4000000059604645,
        0.30769234895706177,
        0.40000003576278687,
        0.5,
        0.8333333134651184,
        0.111111119389534,
        0.4285714626312256,
        0.1666666716337204
      ],
      "fxState": [true, false, true, false, false, false, false, false]
    },
    {
      "type": 3,
      "label": "Drop Piano",
      "volume": 0.5,
      "pan": 0.5,
      "muteState": 0,
      "solo": false,
      "showingAuto": false,
      "currentAutoIndex": 0,
      "scTrackIndex": -1,
      "filePath": "/storage/emulated/0/玩酷电音/SoundFont/Drop piano.sf2",
      "presetIndex": 0,
      "pitchRange": 1,
      "sections": [],
      "autos": [
        { "state": false, "sections": [] },
        { "state": false, "sections": [] },
        { "state": false, "sections": [] },
        { "state": false, "sections": [] },
        { "state": false, "sections": [] },
        { "state": false, "sections": [] },
        { "state": false, "sections": [] },
        { "state": false, "sections": [] },
        { "state": false, "sections": [] },
        { "state": false, "sections": [] },
        { "state": false, "sections": [] }
      ],
      "fx": [
        0,
        0,
        0,
        0.5040004849433899,
        0.5054610967636108,
        0.6000000238418579,
        0.20000000298023224,
        0.49152544140815735,
        0,
        1,
        0.5714285969734192,
        0,
        0.75,
        [0, 0, 0, 0],
        [0.5, 0.5, 0.5, 0.5],
        [
          0.0030030030757188797, 0.011511511169373989, 0.19919919967651367,
          0.5995995998382568
        ],
        [
          0.08994708955287933, 0.05128205567598343, 0.05128205567598343,
          0.08994708955287933
        ],
        1,
        0.07999998331069946,
        0.8000000715255737,
        0,
        0.4000000059604645,
        0,
        0,
        0.75,
        0.4444444477558136,
        0.625,
        0.4000000059604645,
        0.30769234895706177,
        0.40000003576278687,
        0.5,
        0.8333333134651184,
        0.111111119389534,
        0.4285714626312256,
        0.1666666716337204
      ],
      "fxState": [true, false, true, false, false, false, false, false]
    },
    {
      "type": 3,
      "label": "Bowed Glass",
      "volume": 0.5,
      "pan": 0.5,
      "muteState": 0,
      "solo": false,
      "showingAuto": false,
      "currentAutoIndex": 0,
      "scTrackIndex": -1,
      "filePath": "/storage/emulated/0/玩酷电音/SoundFont/Bowed Glass.sf2",
      "presetIndex": 0,
      "pitchRange": 1,
      "sections": [],
      "autos": [
        { "state": false, "sections": [] },
        { "state": false, "sections": [] },
        { "state": false, "sections": [] },
        { "state": false, "sections": [] },
        { "state": false, "sections": [] },
        { "state": false, "sections": [] },
        { "state": false, "sections": [] },
        { "state": false, "sections": [] },
        { "state": false, "sections": [] },
        { "state": false, "sections": [] },
        { "state": false, "sections": [] }
      ],
      "fx": [
        0,
        0,
        0,
        1,
        0.823500394821167,
        0.6000000238418579,
        0.20000000298023224,
        0.49152544140815735,
        0,
        1,
        0.5714285969734192,
        0,
        0.75,
        [0, 0, 0, 0],
        [0.5, 0.5, 0.5, 0.5],
        [
          0.0030030030757188797, 0.011511511169373989, 0.19919919967651367,
          0.5995995998382568
        ],
        [
          0.08994708955287933, 0.05128205567598343, 0.05128205567598343,
          0.08994708955287933
        ],
        1,
        0.07999998331069946,
        0.8000000715255737,
        0,
        0.4000000059604645,
        0,
        0,
        0.75,
        0.4444444477558136,
        0.625,
        0.4000000059604645,
        0.30769234895706177,
        0.40000003576278687,
        0.5,
        0.8333333134651184,
        0.111111119389534,
        0.4285714626312256,
        0.1666666716337204
      ],
      "fxState": [true, false, true, false, false, false, false, false]
    },
    {
      "type": 3,
      "label": "Les Sus_0_30",
      "volume": 0.5,
      "pan": 0.5,
      "muteState": 0,
      "solo": false,
      "showingAuto": false,
      "currentAutoIndex": 0,
      "scTrackIndex": -1,
      "filePath": "/storage/emulated/0/玩酷电音/SoundFont/Touhou.sf2",
      "presetIndex": 30,
      "pitchRange": 1,
      "sections": [],
      "autos": [
        { "state": false, "sections": [] },
        { "state": false, "sections": [] },
        { "state": false, "sections": [] },
        { "state": false, "sections": [] },
        { "state": false, "sections": [] },
        { "state": false, "sections": [] },
        { "state": false, "sections": [] },
        { "state": false, "sections": [] },
        { "state": false, "sections": [] },
        { "state": false, "sections": [] },
        { "state": false, "sections": [] }
      ],
      "fx": [
        0,
        0,
        0,
        0.308500200510025,
        0.30600032210350037,
        0.6000000238418579,
        0.20000000298023224,
        0.49152544140815735,
        0,
        1,
        0.5714285969734192,
        0,
        0.75,
        [0, 0, 0, 0],
        [0.5, 0.5, 0.5, 0.5],
        [
          0.0030030030757188797, 0.011511511169373989, 0.19919919967651367,
          0.5995995998382568
        ],
        [
          0.08994708955287933, 0.05128205567598343, 0.05128205567598343,
          0.08994708955287933
        ],
        1,
        0.07999998331069946,
        0.8000000715255737,
        0,
        0.4000000059604645,
        0,
        0,
        0.75,
        0.4444444477558136,
        0.625,
        0.4000000059604645,
        0.30769234895706177,
        0.40000003576278687,
        0.5,
        0.8333333134651184,
        0.111111119389534,
        0.4285714626312256,
        0.1666666716337204
      ],
      "fxState": [true, false, true, false, false, false, false, false]
    },
    {
      "type": 3,
      "label": "Bass",
      "volume": 0.5,
      "pan": 0.5,
      "muteState": 0,
      "solo": false,
      "showingAuto": false,
      "currentAutoIndex": 0,
      "scTrackIndex": -1,
      "filePath": "/storage/emulated/0/玩酷电音/SoundFont/The_DEFINITIVE_MEGALOVANIA_Soundfont__V1.17.sf2",
      "presetIndex": 13,
      "pitchRange": 1,
      "sections": [
        {
          "startTick": 7680,
          "length": 7680,
          "startOffsetTick": 0,
          "endOffsetTick": 0,
          "notes": [
            { "startTick": 0, "length": 120, "key": 34, "volume": 1 },
            { "startTick": 360, "length": 120, "key": 34, "volume": 1 },
            { "startTick": 480, "length": 120, "key": 36, "volume": 1 },
            { "startTick": 720, "length": 120, "key": 34, "volume": 1 },
            { "startTick": 960, "length": 120, "key": 34, "volume": 1 },
            { "startTick": 1680, "length": 120, "key": 34, "volume": 1 },
            { "startTick": 1320, "length": 120, "key": 36, "volume": 1 },
            { "startTick": 2280, "length": 120, "key": 32, "volume": 1 },
            { "startTick": 2640, "length": 120, "key": 32, "volume": 1 },
            { "startTick": 2880, "length": 120, "key": 32, "volume": 1 },
            { "startTick": 3600, "length": 120, "key": 32, "volume": 1 },
            { "startTick": 1920, "length": 120, "key": 32, "volume": 1 },
            { "startTick": 4200, "length": 120, "key": 30, "volume": 1 },
            { "startTick": 4560, "length": 120, "key": 30, "volume": 1 },
            { "startTick": 4800, "length": 120, "key": 30, "volume": 1 },
            { "startTick": 5520, "length": 120, "key": 30, "volume": 1 },
            { "startTick": 3840, "length": 120, "key": 30, "volume": 1 },
            { "startTick": 6120, "length": 120, "key": 29, "volume": 1 },
            { "startTick": 6480, "length": 120, "key": 29, "volume": 1 },
            { "startTick": 6720, "length": 120, "key": 30, "volume": 1 },
            { "startTick": 7440, "length": 240, "key": 29, "volume": 1 },
            { "startTick": 5760, "length": 120, "key": 29, "volume": 1 },
            { "startTick": 2400, "length": 120, "key": 36, "volume": 1 },
            { "startTick": 3240, "length": 120, "key": 36, "volume": 1 },
            { "startTick": 5160, "length": 120, "key": 34, "volume": 1 },
            { "startTick": 4320, "length": 120, "key": 34, "volume": 1 },
            { "startTick": 6960, "length": 120, "key": 30, "volume": 1 },
            { "startTick": 6240, "length": 120, "key": 34, "volume": 1 },
            { "startTick": 7200, "length": 240, "key": 36, "volume": 1 }
          ]
        }
      ],
      "autos": [
        { "state": false, "sections": [] },
        { "state": false, "sections": [] },
        { "state": false, "sections": [] },
        { "state": false, "sections": [] },
        { "state": false, "sections": [] },
        { "state": false, "sections": [] },
        { "state": false, "sections": [] },
        { "state": false, "sections": [] },
        { "state": false, "sections": [] },
        { "state": false, "sections": [] },
        { "state": false, "sections": [] }
      ],
      "fx": [
        0,
        0,
        0,
        0.3985006809234619,
        0.30708450078964233,
        0.6000000238418579,
        0.20000000298023224,
        0.49152544140815735,
        0,
        1,
        0.5714285969734192,
        0,
        0.75,
        [0, 0, 0, 0],
        [0.5, 0.5, 0.5, 0.5],
        [
          0.0030030030757188797, 0.011511511169373989, 0.19919919967651367,
          0.5995995998382568
        ],
        [
          0.08994708955287933, 0.05128205567598343, 0.05128205567598343,
          0.08994708955287933
        ],
        1,
        0.07999998331069946,
        0.8000000715255737,
        0,
        0.4000000059604645,
        0,
        0,
        0.75,
        0.4444444477558136,
        0.625,
        0.4000000059604645,
        0.30769234895706177,
        0.40000003576278687,
        0.5,
        0.8333333134651184,
        0.111111119389534,
        0.4285714626312256,
        0.1666666716337204
      ],
      "fxState": [true, false, true, false, false, false, false, false]
    },
    {
      "type": 3,
      "label": "LEAD 1",
      "volume": 0.5,
      "pan": 0.5,
      "muteState": 0,
      "solo": false,
      "showingAuto": false,
      "currentAutoIndex": 0,
      "scTrackIndex": -1,
      "filePath": "/storage/emulated/0/玩酷电音/SoundFont/8bitlate.sf2",
      "presetIndex": 87,
      "pitchRange": 1,
      "sections": [],
      "autos": [
        { "state": false, "sections": [] },
        { "state": false, "sections": [] },
        { "state": false, "sections": [] },
        { "state": false, "sections": [] },
        { "state": false, "sections": [] },
        { "state": false, "sections": [] },
        { "state": false, "sections": [] },
        { "state": false, "sections": [] },
        { "state": false, "sections": [] },
        { "state": false, "sections": [] },
        { "state": false, "sections": [] }
      ],
      "fx": [
        0,
        0,
        0.005500000435858965,
        0.6030002236366272,
        0.602963387966156,
        0.6000000238418579,
        0.20000000298023224,
        0.49152544140815735,
        0,
        1,
        0.5714285969734192,
        0,
        0.75,
        [0, 0, 0, 0],
        [0.5, 0.5, 0.5, 0.5],
        [
          0.0030030030757188797, 0.011511511169373989, 0.19919919967651367,
          0.5995995998382568
        ],
        [
          0.08994708955287933, 0.05128205567598343, 0.05128205567598343,
          0.08994708955287933
        ],
        1,
        0.07999998331069946,
        0.8000000715255737,
        0,
        0.4000000059604645,
        0,
        0,
        0.75,
        0.4444444477558136,
        0.625,
        0.4000000059604645,
        0.30769234895706177,
        0.40000003576278687,
        0.5,
        0.8333333134651184,
        0.111111119389534,
        0.4285714626312256,
        0.1666666716337204
      ],
      "fxState": [true, false, true, false, false, false, false, false]
    },
    {
      "type": 1,
      "label": "鼓组",
      "volume": 0.5,
      "pan": 0.5,
      "muteState": 0,
      "solo": false,
      "showingAuto": false,
      "currentAutoIndex": 0,
      "scTrackIndex": -1,
      "channels": [
        {
          "fileName": "Sweep Up 2",
          "soundPack": "BasicSoundPack",
          "volume": 1,
          "pan": 0.5
        }
      ],
      "sections": [],
      "autos": [
        { "state": false, "sections": [] },
        { "state": false, "sections": [] },
        { "state": false, "sections": [] },
        { "state": false, "sections": [] },
        { "state": false, "sections": [] },
        { "state": false, "sections": [] },
        { "state": false, "sections": [] },
        { "state": false, "sections": [] },
        { "state": false, "sections": [] },
        { "state": false, "sections": [] },
        { "state": false, "sections": [] }
      ],
      "fx": [
        0,
        0,
        0,
        0.6314999461174011,
        0.6285001635551453,
        0.6000000238418579,
        0.20000000298023224,
        0.49152544140815735,
        0,
        1,
        0.5714285969734192,
        0,
        0.75,
        [0, 0, 0, 0],
        [0.5, 0.5, 0.5, 0.5],
        [
          0.0030030030757188797, 0.011511511169373989, 0.19919919967651367,
          0.5995995998382568
        ],
        [
          0.08994708955287933, 0.05128205567598343, 0.05128205567598343,
          0.08994708955287933
        ],
        1,
        0.07999998331069946,
        0.8000000715255737,
        0,
        0.4000000059604645,
        0,
        0,
        0.75,
        0.4444444477558136,
        0.625,
        0.4000000059604645,
        0.30769234895706177,
        0.40000003576278687,
        0.5,
        0.8333333134651184,
        0.111111119389534,
        0.4285714626312256,
        0.1666666716337204
      ],
      "fxState": [true, false, true, false, false, false, false, false]
    },
    {
      "type": 3,
      "label": "Violin Detache",
      "volume": 0.5,
      "pan": 0.5,
      "muteState": 0,
      "solo": false,
      "showingAuto": false,
      "currentAutoIndex": 0,
      "scTrackIndex": -1,
      "filePath": "/storage/emulated/0/玩酷电音/SoundFont/Violin Detache.sf2",
      "presetIndex": 0,
      "pitchRange": 1,
      "sections": [],
      "autos": [
        { "state": false, "sections": [] },
        { "state": false, "sections": [] },
        { "state": false, "sections": [] },
        { "state": false, "sections": [] },
        { "state": false, "sections": [] },
        { "state": false, "sections": [] },
        { "state": false, "sections": [] },
        { "state": false, "sections": [] },
        { "state": false, "sections": [] },
        { "state": false, "sections": [] },
        { "state": false, "sections": [] }
      ],
      "fx": [
        0,
        0,
        0,
        0.6070008873939514,
        0.6069886684417725,
        0.6000000238418579,
        0.20000000298023224,
        0.49152544140815735,
        0,
        1,
        0.5714285969734192,
        0,
        0.75,
        [0, 0, 0, 0],
        [0.5, 0.5, 0.5, 0.5],
        [
          0.0030030030757188797, 0.011511511169373989, 0.19919919967651367,
          0.5995995998382568
        ],
        [
          0.08994708955287933, 0.05128205567598343, 0.05128205567598343,
          0.08994708955287933
        ],
        1,
        0.07999998331069946,
        0.8000000715255737,
        0,
        0.4000000059604645,
        0,
        0,
        0.75,
        0.4444444477558136,
        0.625,
        0.4000000059604645,
        0.30769234895706177,
        0.40000003576278687,
        0.5,
        0.8333333134651184,
        0.111111119389534,
        0.4285714626312256,
        0.1666666716337204
      ],
      "fxState": [true, false, true, false, false, false, false, false]
    },
    {
      "type": 3,
      "label": "STANDARD 1",
      "volume": 0.5,
      "pan": 0.5,
      "muteState": 0,
      "solo": false,
      "showingAuto": false,
      "currentAutoIndex": 0,
      "scTrackIndex": -1,
      "filePath": "/storage/emulated/0/玩酷电音/SoundFont/THDrum.sf2",
      "presetIndex": 0,
      "pitchRange": 1,
      "sections": [],
      "autos": [
        { "state": false, "sections": [] },
        { "state": false, "sections": [] },
        { "state": false, "sections": [] },
        { "state": false, "sections": [] },
        { "state": false, "sections": [] },
        { "state": false, "sections": [] },
        { "state": false, "sections": [] },
        { "state": false, "sections": [] },
        { "state": false, "sections": [] },
        { "state": false, "sections": [] },
        { "state": false, "sections": [] }
      ],
      "fx": [
        0,
        0,
        0,
        1,
        1,
        0.6000000238418579,
        0.20000000298023224,
        0.49152544140815735,
        0,
        1,
        0.5714285969734192,
        0,
        0.75,
        [0, 0, 0, 0],
        [0.5, 0.5, 0.5, 0.5],
        [
          0.0030030030757188797, 0.011511511169373989, 0.19919919967651367,
          0.5995995998382568
        ],
        [
          0.08994708955287933, 0.05128205567598343, 0.05128205567598343,
          0.08994708955287933
        ],
        1,
        0.07999998331069946,
        0.8000000715255737,
        0,
        0.4000000059604645,
        0,
        0,
        0.75,
        0.4444444477558136,
        0.625,
        0.4000000059604645,
        0.30769234895706177,
        0.40000003576278687,
        0.5,
        0.8333333134651184,
        0.111111119389534,
        0.4285714626312256,
        0.1666666716337204
      ],
      "fxState": [true, false, true, false, false, false, false, false]
    }
  ]
}
